{"BaseModel.7588df40-6775-47bf-becf-7e0599b09a6c": {"id": "7588df40-6775-47bf-becf-7e0599b09a6c", "created_at": "2023-03-14T23:43:29.938732", "updated_at": "2023-03-14T23:43:29.938878", "__class__": "BaseModel"}, "Place.9e722c6c-46db-4af4-a95a-0f64a2f1114f": {"id": "9e722c6c-46db-4af4-a95a-0f64a2f1114f", "created_at": "2023-03-14T23:43:35.020451", "updated_at": "2023-03-14T23:43:35.020590", "city_id": "", "user_id": "", "description": "", "number_rooms": 0, "number_bathrooms": 0, "max_guest": 0, "price_by_nigt": 0, "latitude": 0.0, "longitude": 0.0, "amenity_ids": "", "name": "", "__class__": "Place"}, "State.82fe9226-f647-4098-b698-2ed08c524a64": {"id": "82fe9226-f647-4098-b698-2ed08c524a64", "created_at": "2023-03-14T23:43:39.111003", "updated_at": "2023-03-14T23:43:39.111163", "name": "", "__class__": "State"}, "City.8f5c71b3-618f-48a8-8958-9b9ab305e847": {"id": "8f5c71b3-618f-48a8-8958-9b9ab305e847", "created_at": "2023-03-14T23:43:46.853133", "updated_at": "2023-03-14T23:43:46.853247", "state_id": "", "name": "", "__class__": "City"}}